{
  "posts": [
    {
      "id": 1,
      "title": "json-server",
      "author": "typicode"
    }
  ],
  "comments": [
    {
      "id": 1,
      "body": "some comment",
      "postId": 1
    }
  ],
  "profile": {
    "name": "typicode"
  },
  "nhaxes": [
    {
      "id": 1,
      "tenNhaXe": "Phương Trang"
    },
    {
      "id": 2,
      "tenNhaXe": "Trung Nguyên"
    },
    {
      "id": 3,
      "tenNhaXe": "Trung Tín"
    }
  ],
  "vexes": [
    {
      "giaVe": "1000000",
      "diemDi": "Đà Nẵng",
      "diemDen": "Huế",
      "ngayDi": "06/09/2021",
      "gioDi": "20:00",
      "nhaxe": {
        "id": 1,
        "tenNhaXe": "Phương Trang"
      },
      "soLuong": 10,
      "id": 1
    },
    {
      "id": 2,
      "giaVe": 5000000,
      "diemDi": "Đà Nẵng",
      "diemDen": "Hải Phòng",
      "ngayDi": "10/09/2021",
      "gioDi": "06:00",
      "nhaxe": {
        "id": 2,
        "tenNhaXe": "Trung Nguyên"
      },
      "soLuong": 5
    },
    {
      "id": 3,
      "giaVe": 4500000,
      "diemDi": "Đà Nẵng",
      "diemDen": "Hà Nội",
      "ngayDi": "09/10/2021",
      "gioDi": "07:40",
      "nhaxe": {
        "id": 3,
        "tenNhaXe": "Trung Tín"
      },
      "soLuong": 15
    },
    {
      "name": "",
      "giaVe": "4343",
      "diemDi": "fdf",
      "diemDen": "fdfdf",
      "ngayDi": "4434",
      "gioDi": "434",
      "nhaxe": {
        "id": 1,
        "tenNhaXe": "Phương Trang"
      },
      "soLuong": "4",
      "id": 4
    }
  ]
}